easytrader/__init__.py
easytrader/api.py
easytrader/clienttrader.py
easytrader/exceptions.py
easytrader/follower.py
easytrader/gf_clienttrader.py
easytrader/gj_clienttrader.py
easytrader/grid_strategies.py
easytrader/ht_clienttrader.py
easytrader/htzq_clienttrader.py
easytrader/joinquant_follower.py
easytrader/log.py
easytrader/pop_dialog_handler.py
easytrader/refresh_strategies.py
easytrader/remoteclient.py
easytrader/ricequant_follower.py
easytrader/server.py
easytrader/universal_clienttrader.py
easytrader/webtrader.py
easytrader/wk_clienttrader.py
easytrader/xq_follower.py
easytrader/xqtrader.py
easytrader/yh_clienttrader.py
easytrader/config/__init__.py
easytrader/config/client.py
easytrader/config/global.json
easytrader/config/xq.json
easytrader/utils/__init__.py
easytrader/utils/captcha.py
easytrader/utils/misc.py
easytrader/utils/perf.py
easytrader/utils/stock.py
easytrader/utils/win_gui.py
newEasytrader-0.23.1.dist-info/LICENSE
newEasytrader-0.23.1.dist-info/METADATA
newEasytrader-0.23.1.dist-info/WHEEL
newEasytrader-0.23.1.dist-info/top_level.txt
newEasytrader-0.23.1.dist-info/RECORD
