Metadata-Version: 2.2
Name: newEasytrader
Version: 0.23.1
Summary: A utility for China Stock Trade
Home-page: https://github.com/yiliang114/easytrader
Author: yiliang114
Author-email: 1204183885@qq.com
License: BSD
Keywords: China stock trade
Classifier: Development Status :: 4 - Beta
Classifier: Programming Language :: Python :: 2.6
Classifier: Programming Language :: Python :: 2.7
Classifier: Programming Language :: Python :: 3.2
Classifier: Programming Language :: Python :: 3.3
Classifier: Programming Language :: Python :: 3.4
Classifier: Programming Language :: Python :: 3.5
Classifier: License :: OSI Approved :: BSD License
License-File: LICENSE
Requires-Dist: requests
Requires-Dist: six
Requires-Dist: easyutils
Requires-Dist: flask
Requires-Dist: pywinauto==0.6.6
Requires-Dist: pillow
Requires-Dist: pandas
Dynamic: author
Dynamic: author-email
Dynamic: classifier
Dynamic: description
Dynamic: home-page
Dynamic: keywords
Dynamic: license
Dynamic: requires-dist
Dynamic: summary
